{
  "@context": "000_context.jsonld",
  "id": "pelagic_interaction_scheme_for_carbon_and_ecosystem_studies_model_volume_2_version_trace_gases_piscesv2_gas_hgrid_1",
  "type": "horizontal_grid_cell",
  "name": "Pelagic Interaction Scheme for Carbon and Ecosystem Studies model volume 2 version trace gases (PISCESv2-gas)_hgrid_1",
  "region": "global",
  "grid_type": "tripolar",
  "grid_mapping": "",
  "temporal_refinement": "static",
  "description": "eORCA1L75",
  "x_resolution": null,
  "y_resolution": null,
  "horizontal_units": null,
  "southernmost_latitude": null,
  "westernmost_longitude": null,
  "n_cells": 105704,
  "truncation_method": null,
  "truncation_number": null,
  "drs_name": "Pelagic Interaction Scheme for Carbon and Ecosystem Studies model volume 2 version trace gases (PISCESv2-gas)_hgrid_1"
}