{
    "@context": "000_context.jsonld",
    "id": "mpi-b",
    "type": "institution",
    "drs_name": "MPI-B",
    "acronyms": [],
    "labels": [
        "Max Planck Institute for Biogeochemistry"
    ],
    "description": "Max Planck Institute for Biogeochemistry",
    "location": [
        {
            "city": "Jena",
            "country": "Germany",
            "lat": 50.910556,
            "lon": 11.567222
        }
    ],
    "ror": "051yxp643",
    "urls": [
        "http://www.bgc-jena.mpg.de/"
    ]
}
